polypie.py
polypie-0.2.0.dist-info/LICENSE
polypie-0.2.0.dist-info/METADATA
polypie-0.2.0.dist-info/WHEEL
polypie-0.2.0.dist-info/top_level.txt
polypie-0.2.0.dist-info/RECORD
