Metadata-Version: 2.1
Name: polypie
Version: 0.2.0
Summary: Python polymorphic function declaration with obvious syntax
Home-page: https://github.com/un-def/polypie
Author: un.def
Author-email: me@undef.im
License: BSD License
Platform: UNKNOWN
Classifier: Intended Audience :: Developers
Classifier: License :: OSI Approved :: BSD License
Classifier: Operating System :: OS Independent
Classifier: Programming Language :: Python :: 3
Classifier: Programming Language :: Python :: 3.5
Classifier: Programming Language :: Python :: 3.6
Classifier: Programming Language :: Python :: 3.7
Classifier: Topic :: Software Development :: Libraries
Classifier: Topic :: Utilities
Requires-Python: >=3.5
Requires-Dist: typeguard
